LICENSE
README.md
setup.py
blitzgsea/__init__.py
blitzgsea/enrichr.py
blitzgsea/mpsci.py
blitzgsea/plot.py
blitzgsea/shuffle.py
blitzgsea/signature_similarity.py
blitzgsea.egg-info/PKG-INFO
blitzgsea.egg-info/SOURCES.txt
blitzgsea.egg-info/dependency_links.txt
blitzgsea.egg-info/requires.txt
blitzgsea.egg-info/top_level.txt
blitzgsea/data/GO_Biological_Process_2023
blitzgsea/data/KEGG_2021_Human
blitzgsea/data/config.json