Metadata-Version: 2.1
Name: blitzgsea
Version: 1.3.54
Summary: Package for fast and accurate calculation of Gene Set Enrichment Analysis (GSEA) similar to prerank using gamma distribution approximation.
Home-page: https://github.com/maayanlab/blitzgsea
Author: Alexander Lachmann
Author-email: alexander.lachmann@mssm.edu
Classifier: Programming Language :: Python :: 3
Classifier: License :: OSI Approved :: Apache Software License
Classifier: Operating System :: OS Independent
Requires-Python: >=3.6
License-File: LICENSE
